README.rst
setup.py
jw/__init__.py
jw.backup.egg-info/PKG-INFO
jw.backup.egg-info/SOURCES.txt
jw.backup.egg-info/dependency_links.txt
jw.backup.egg-info/entry_points.txt
jw.backup.egg-info/namespace_packages.txt
jw.backup.egg-info/requires.txt
jw.backup.egg-info/top_level.txt
jw/backup/__init__.py
jw/backup/main.py
jw/backup/os/__init__.py
jw/backup/os/base.py
jw/backup/os/dpkg.py
jw/backup/os/portage.py