Metadata-Version: 1.1
Name: jw.backup
Version: 1.0.6
Summary: A simple differential backup script for systems maintained bypackage managers with single-file manifests
Home-page: https://pypi.python.org/pypi/jw.backup
Author: Johnny Wezel
Author-email: dev-jay@wezel.name
License: GPL
Download-URL: https://pypi.python.org/packages/source/j/jw.backup/jw.backup-1.0.6.tar.gz
Keywords: backup,utility
Platform: POSIX
Classifier: Development Status :: 5 - Production/Stable
Classifier: Environment :: Console
Classifier: Intended Audience :: System Administrators
Classifier: License :: OSI Approved :: GNU General Public License v3 or later (GPLv3+)
Classifier: Natural Language :: English
Classifier: Operating System :: POSIX
Classifier: Programming Language :: Python :: 2
Classifier: Programming Language :: Python :: 2.7
Classifier: Programming Language :: Python :: 3
Classifier: Programming Language :: Python :: 3.4
Classifier: Topic :: System :: Archiving :: Backup
Classifier: Topic :: System :: Archiving :: Mirroring
Classifier: Topic :: Utilities
